{
  "version": "7",
  "dialect": "postgresql",
  "entries": [
    {
      "idx": 0,
      "version": "7",
      "when": 1742460798129,
      "tag": "0000_broad_genesis",
      "breakpoints": true
    },
    {
      "idx": 1,
      "version": "7",
      "when": 1742462702634,
      "tag": "0001_same_cyclops",
      "breakpoints": true
    },
    {
      "idx": 2,
      "version": "7",
      "when": 1742466094221,
      "tag": "0002_aspiring_hardball",
      "breakpoints": true
    },
    {
      "idx": 3,
      "version": "7",
      "when": 1742466138965,
      "tag": "0003_tricky_frog_thor",
      "breakpoints": true
    },
    {
      "idx": 4,
      "version": "7",
      "when": 1742466472437,
      "tag": "0004_dark_microchip",
      "breakpoints": true
    },
    {
      "idx": 5,
      "version": "7",
      "when": 1742466682741,
      "tag": "0005_material_spot",
      "breakpoints": true
    },
    {
      "idx": 6,
      "version": "7",
      "when": 1742467148920,
      "tag": "0006_calm_morph",
      "breakpoints": true
    },
    {
      "idx": 7,
      "version": "7",
      "when": 1742468366899,
      "tag": "0007_dashing_wilson_fisk",
      "breakpoints": true
    }
  ]
}